payload_redactor/__init__.py
payload_redactor/redaction.py
payload_redactor/structlog_adapter.py
payload_redactor-0.1.0.dist-info/licenses/LICENSE
payload_redactor-0.1.0.dist-info/METADATA
payload_redactor-0.1.0.dist-info/WHEEL
payload_redactor-0.1.0.dist-info/top_level.txt
payload_redactor-0.1.0.dist-info/RECORD
