Metadata-Version: 2.4
Name: payload-redactor
Version: 0.1.0
Summary: Pure-function helpers for redacting structured payloads.
Author-email: Lars de Ridder <lars@xithing.io>
License: MIT
Project-URL: Homepage, https://github.com/larsderidder/payload-redactor
Project-URL: Documentation, https://github.com/larsderidder/payload-redactor
Keywords: redaction,scrubbing,logging,privacy,security,structlog
Classifier: Development Status :: 4 - Beta
Classifier: Intended Audience :: Developers
Classifier: License :: OSI Approved :: MIT License
Classifier: Programming Language :: Python :: 3
Classifier: Programming Language :: Python :: 3.8
Classifier: Programming Language :: Python :: 3.9
Classifier: Programming Language :: Python :: 3.10
Classifier: Programming Language :: Python :: 3.11
Classifier: Programming Language :: Python :: 3.12
Classifier: Topic :: Software Development :: Libraries
Classifier: Topic :: System :: Logging
Classifier: Typing :: Typed
Requires-Python: >=3.8
License-File: LICENSE
Provides-Extra: dev
Requires-Dist: black; extra == "dev"
Requires-Dist: pytest; extra == "dev"
Provides-Extra: structlog
Requires-Dist: structlog>=23.2; extra == "structlog"
Dynamic: license-file
